jupyxplorer/__init__.py
jupyxplorer/docker.py
jupyxplorer/main.py
jupyxplorer/parser.py
jupyxplorer/notebooks/cat.ipynb
jupyxplorer/notebooks/num.ipynb
jupyxplorer/processors/__init__.py
tests/__init__.py
jupyXplorer-0.0.4.dist-info/LICENSE
jupyXplorer-0.0.4.dist-info/METADATA
jupyXplorer-0.0.4.dist-info/WHEEL
jupyXplorer-0.0.4.dist-info/entry_points.txt
jupyXplorer-0.0.4.dist-info/top_level.txt
jupyXplorer-0.0.4.dist-info/RECORD
