Metadata-Version: 2.1
Name: jupyXplorer
Version: 0.0.4
Summary: jupyXplorer: notebooks generator from data
Home-page: https://github.com/hypnosapos/jupyXplorer
Author: Hypnosapos
License: MIT
Platform: UNKNOWN
Classifier: License :: OSI Approved :: MIT License
Classifier: Programming Language :: Python :: 3.5
Classifier: Programming Language :: Python :: 3.6
Classifier: Programming Language :: Python :: 3.7
Classifier: Topic :: Software Development :: Libraries :: Python Modules
Classifier: Topic :: Scientific/Engineering :: Information Analysis
Requires-Python: >=3.5
Requires-Dist: PyYAML (==4.2b4)
Requires-Dist: cerberus (==1.2)
Requires-Dist: nbconvert (==5.4.0)
Requires-Dist: docker (==3.6.0)
